{
  "captures": [
    {
      "encoding": "utf-8",
      "id": "stderr.raw",
      "inline_text": "src/main.cpp: In function 'int main()':\nsrc/main.cpp:5:17: error: invalid conversion from 'const char*' to 'short int' [-fpermissive]\n    5 |     takes_short(\"x\");\n      |                 ^~~\n      |                 |\n      |                 const char*\nsrc/main.cpp:1:18: note: initializing argument 1 of 'void takes_short(short int)'\n    1 | void takes_short(short);\n      |                  ^~~~~\n",
      "kind": "compiler_stderr_text",
      "media_type": "text/plain",
      "produced_by": {
        "name": "g++",
        "vendor": "GNU"
      },
      "size_bytes": 400,
      "storage": "inline"
    },
    {
      "encoding": "utf-8",
      "external_ref": "<capture:diagnostics.sarif>",
      "id": "diagnostics.sarif",
      "kind": "gcc_sarif",
      "media_type": "application/sarif+json",
      "produced_by": {
        "name": "g++",
        "vendor": "GNU"
      },
      "size_bytes": 5223,
      "storage": "external_ref"
    }
  ],
  "diagnostics": [
    {
      "analysis": {
        "confidence": "medium",
        "family": "type_overload",
        "first_action_hint": "compare the expected type and actual argument at the call site",
        "headline": "type or overload mismatch",
        "matched_conditions": [
          "phase=semantic",
          "message_contains=invalid conversion"
        ],
        "rule_id": "rule.family.type_overload.structured_or_message"
      },
      "fingerprints": {
        "family": "6a2a5e104cee19b7cd847cc021698709de0696d15a43dbf7f2d52d88baaebc6a",
        "raw": "6dfc7f826c76e7631d308e3dbf22bf07896113e1f1d07e6d7843c617e5d19a74",
        "structural": "6980e10a65b340c9fe2eec30b959adbb1a905525ac9b90e8e222cd79b7c53b4d"
      },
      "id": "sarif-0-0",
      "locations": [
        {
          "column": 17,
          "end_column": 20,
          "line": 5,
          "ownership": "user",
          "path": "src/main.cpp"
        }
      ],
      "message": {
        "raw_text": "invalid conversion from 'const char*' to 'short int'"
      },
      "node_completeness": "complete",
      "origin": "gcc",
      "phase": "semantic",
      "provenance": {
        "capture_refs": [
          "diagnostics.sarif"
        ],
        "source": "compiler"
      },
      "semantic_role": "root",
      "severity": "error"
    },
    {
      "analysis": {
        "confidence": "low",
        "family": "unknown",
        "first_action_hint": "inspect the preserved raw diagnostics for the first corrective action",
        "headline": "initializing argument 1 of 'void takes_short(short int)'",
        "matched_conditions": [
          "no_family_rule_matched"
        ],
        "rule_id": "rule.family.unknown",
        "suppression_reason": "generic_fallback"
      },
      "fingerprints": {
        "family": "e1f81f2eeec82216cd3e5caaac1d91b70a9a055d5c73aa656a7db763cc350a17",
        "raw": "aa73c4d7a4d40bdc6a0f07d075267e76fec3eed699e62de0c306715349ee6fa6",
        "structural": "ba1906976e8a8efa85b18aad032f91f8f0f8942dd8caa590fb7cb5363f03e57b"
      },
      "id": "sarif-0-1",
      "locations": [
        {
          "column": 18,
          "end_column": 23,
          "line": 1,
          "ownership": "user",
          "path": "src/main.cpp"
        }
      ],
      "message": {
        "raw_text": "initializing argument 1 of 'void takes_short(short int)'"
      },
      "node_completeness": "complete",
      "origin": "gcc",
      "phase": "semantic",
      "provenance": {
        "capture_refs": [
          "diagnostics.sarif"
        ],
        "source": "compiler"
      },
      "semantic_role": "root",
      "severity": "note"
    }
  ],
  "document_completeness": "complete",
  "document_id": "<document>",
  "fingerprints": {
    "family": "379ee7ec878c5418c1b1c12dd21335eed2370cafcc85d900d2afbe5b31758c93",
    "raw": "d96bda940dc47d4f2760f5dec05f2d49b4e7ac9c7d623f40493ddf0ff7ff75df",
    "structural": "18af372ad640c340d97db6b60fe402400edc7c2acc177bf40b81139fc77f41d0"
  },
  "producer": {
    "name": "gcc-formed",
    "rulepack_version": "phase1",
    "version": "<normalized>"
  },
  "run": {
    "argv_redacted": [
      "g++",
      "-std=c++17",
      "-c",
      "src/main.cpp"
    ],
    "cwd_display": "<cwd>",
    "exit_status": 1,
    "invocation_id": "<invocation>",
    "invoked_as": "gcc-formed",
    "language_mode": "cpp",
    "primary_tool": {
      "name": "g++",
      "vendor": "GNU"
    },
    "target_triple": "x86_64-unknown-linux-gnu",
    "wrapper_mode": "terminal"
  },
  "schema_version": "1.0.0-alpha.1"
}